<?xml version="1.0" encoding="utf-8" ?><dwsync><file name="jquery.easing.min.js" server="ipage.defaga.com" local="3531564938" remote="3534021060" Dst="-1" /><file name="grayscale.js" server="ipage.defaga.com" local="3536083867" remote="3536080380" Dst="-1" /><file name="jquery.easing.min.js" server="ssh.phx.nearlyfreespeech.net" local="3531564938" remote="3536253657" Dst="-1" /><file name="grayscale.js" server="ssh.phx.nearlyfreespeech.net" local="3537042137" remote="3537044913" Dst="-1" /><file name=".DS_Store" server="ssh.phx.nearlyfreespeech.net" local="3536605774" remote="3536605922" Dst="-1" /><file name="bootstrap.js" server="ssh.phx.nearlyfreespeech.net" local="3531564938" remote="3536605922" Dst="-1" /><file name="bootstrap.min.js" server="ssh.phx.nearlyfreespeech.net" local="3531564938" remote="3536605923" Dst="-1" /><file name="jquery.js" server="ssh.phx.nearlyfreespeech.net" local="3531564938" remote="3536605923" Dst="-1" /></dwsync>